{
	"configurations" : 
	[
		{
			"directories" : 
			[
				{
					"build" : ".",
					"jsonFile" : "directory-.-Debug-f5ebdc15457944623624.json",
					"minimumCMakeVersion" : 
					{
						"string" : "3.5"
					},
					"projectIndex" : 0,
					"source" : ".",
					"targetIndexes" : 
					[
						0
					]
				}
			],
			"name" : "Debug",
			"projects" : 
			[
				{
					"directoryIndexes" : 
					[
						0
					],
					"name" : "kolokvij_1",
					"targetIndexes" : 
					[
						0
					]
				}
			],
			"targets" : 
			[
				{
					"directoryIndex" : 0,
					"id" : "Zadatak2::@6890427a1f51a3e7e1df",
					"jsonFile" : "target-Zadatak2-Debug-ad66430e76c460406a81.json",
					"name" : "Zadatak2",
					"projectIndex" : 0
				}
			]
		}
	],
	"kind" : "codemodel",
	"paths" : 
	{
		"build" : "/home/khartl/FSB/semestar_8/algoritmi_strojnog_vida/kolokvij_1/build",
		"source" : "/home/khartl/FSB/semestar_8/algoritmi_strojnog_vida/kolokvij_1"
	},
	"version" : 
	{
		"major" : 2,
		"minor" : 6
	}
}
